{
  "id": "cranberry",
  "cardNumber": 14,
  "name": "Журавлині",
  "nameEn": "cranberry",
  "tags": [
    "міцні",
    "ягідні",
    "кислі"
  ],
  "ingredients": [
    {
      "name": "Лондонський сухий джин",
      "amount": 30,
      "unit": "мл"
    },
    {
      "name": "Рожевий вермут Martini",
      "amount": 15,
      "unit": "мл"
    },
    {
      "name": "Гренадін",
      "amount": 5,
      "unit": "мл"
    },
    {
      "name": "Лаймовий сік",
      "amount": 10,
      "unit": "мл"
    },
    {
      "name": "Журавлина",
      "amount": 15,
      "unit": "г"
    },
    {
      "name": "Цукрова пудра",
      "amount": 1,
      "unit": "г"
    },
    {
      "name": "Лід подрібнений",
      "amount": 150,
      "unit": "г"
    }
  ],
  "tools": [
    "Джигер",
    "Ложка",
    "Гейзер",
    "Мадлер",
    "Сквізер",
    "Трубочки 2 шт."
  ],
  "steps": [
    "Поклади до роксу журавлину 2 к. ложки та потисни мадлером.",
    "Наповни рокс подрібненим льодом доверху.",
    "Налий лаймовий сік 10мл, гренадин 5 мл, трояндовий вермут 15 мл і джин 30 мл.",
    "Розмішай коктейльною ложкою і досип трохи дробленого льоду.",
    "Прикрась журавлиною і цукровою пудрою."
  ],
  "glass": "рокс",
  "images": {
    "front": "front.webp",
    "back": "back.webp"
  },
  "source": {
    "front": "IMG_3103.HEIC",
    "back": "IMG_3104.HEIC"
  }
}
